DuansheliX3/README.md
DuansheliX3/__init__.py
DuansheliX3/__main__.py
DuansheliX3/file.epub
DuansheliX3/index.html
DuansheliX3/css/__init__.py
DuansheliX3/css/annotations.css
DuansheliX3/css/main.css
DuansheliX3/css/normalize.css
DuansheliX3/css/popup.css
DuansheliX3/font/__init__.py
DuansheliX3/font/fontello.eot
DuansheliX3/font/fontello.svg
DuansheliX3/font/fontello.ttf
DuansheliX3/font/fontello.woff
DuansheliX3/img/__init__.py
DuansheliX3/img/annotator-glyph-sprite.png
DuansheliX3/img/annotator-icon-sprite.png
DuansheliX3/img/apple-touch-icon.png
DuansheliX3/img/cancelfullscreen.png
DuansheliX3/img/close.png
DuansheliX3/img/fullscreen.png
DuansheliX3/img/loader.gif
DuansheliX3/img/menu-icon.png
DuansheliX3/img/save.png
DuansheliX3/img/saved.png
DuansheliX3/img/settings-s.png
DuansheliX3/img/settings.png
DuansheliX3/img/star.png
DuansheliX3/js/__init__.py
DuansheliX3/js/epub.js
DuansheliX3/js/epub.min.js
DuansheliX3/js/epub.min.map
DuansheliX3/js/hooks.min.js
DuansheliX3/js/hooks.min.map
DuansheliX3/js/reader.js
DuansheliX3/js/reader.js.map
DuansheliX3/js/reader.min.js
DuansheliX3/js/reader.min.map
DuansheliX3/js/hooks/__init__.py
DuansheliX3/js/hooks/extensions/__init__.py
DuansheliX3/js/hooks/extensions/highlight.js
DuansheliX3/js/libs/__init__.py
DuansheliX3/js/libs/jquery.min.js
DuansheliX3/js/libs/localforage.min.js
DuansheliX3/js/libs/screenfull.js
DuansheliX3/js/libs/screenfull.min.js
DuansheliX3/js/libs/zip.min.js
DuansheliX3/js/plugins/__init__.py
DuansheliX3/js/plugins/hypothesis.js
DuansheliX3/js/plugins/search.js
duansheli_x3-2022.10.15.0.dist-info/METADATA
duansheli_x3-2022.10.15.0.dist-info/WHEEL
duansheli_x3-2022.10.15.0.dist-info/entry_points.txt
duansheli_x3-2022.10.15.0.dist-info/top_level.txt
duansheli_x3-2022.10.15.0.dist-info/RECORD
